LICENSE
MANIFEST.in
README.md
setup.py
graph_db/__init__.py
graph_db/types.py
graph_db.egg-info/PKG-INFO
graph_db.egg-info/SOURCES.txt
graph_db.egg-info/dependency_links.txt
graph_db.egg-info/requires.txt
graph_db.egg-info/top_level.txt
graph_db/driver/__init__.py
graph_db/driver/__pycache__/__init__.cpython-34.pyc
graph_db/driver/orientdb/__init__.py
graph_db/driver/orientdb/driver.py
graph_db/driver/orientdb/edge.py
graph_db/driver/orientdb/exceptions.py
graph_db/driver/orientdb/result.py
graph_db/driver/orientdb/vertex.py
graph_db/driver/orientdb/__pycache__/__init__.cpython-34.pyc
graph_db/driver/orientdb/__pycache__/driver.cpython-34.pyc
graph_db/driver/orientdb/__pycache__/edge.cpython-34.pyc
graph_db/driver/orientdb/__pycache__/exceptions.cpython-34.pyc
graph_db/driver/orientdb/__pycache__/result.cpython-34.pyc
graph_db/driver/orientdb/__pycache__/vertex.cpython-34.pyc