Metadata-Version: 1.1
Name: graph-db
Version: 0.0.3
Summary: GraphDB almacenamiento para grafos en cualquier gestor de base de datos.
Home-page: http://github.com/josegomezr/graph_db
Author: José Daniel Gómez Rodríguez
Author-email: 1josegomezr@gmail.com
License: Apache Software License
Keywords: graph database grafos
Platform: any
Classifier: Programming Language :: Python
Classifier: Development Status :: 3 - Alpha
Classifier: Natural Language :: Spanish
Classifier: Intended Audience :: Developers
Classifier: License :: OSI Approved :: Apache Software License
Classifier: Operating System :: OS Independent
Classifier: Topic :: Software Development :: Libraries :: Python Modules
Classifier: Topic :: Software Development :: Libraries :: Application Frameworks
